LICENSE
MANIFEST.in
README.md
setup.py
cryomethods/__init__.py
cryomethods/bibtex.py
cryomethods/constants.py
cryomethods/convert.py
cryomethods/functions.py
cryomethods/viewers.py
cryomethods/wizards.py
cryomethods/protocols/__init__.py
cryomethods/protocols/protocol_base.py
cryomethods/protocols/protocol_volume_selector.py
cryomethods/tests/__init__.py
cryomethods/tests/test_protocols_cryomethods.py
scipion_em_cryomethods.egg-info/PKG-INFO
scipion_em_cryomethods.egg-info/SOURCES.txt
scipion_em_cryomethods.egg-info/dependency_links.txt
scipion_em_cryomethods.egg-info/top_level.txt