Metadata-Version: 1.1
Name: scipion-em-cryomethods
Version: 1.1.1
Summary: Plugin to use Cryomethods program within the Scipion framework
Home-page: https://github.com/mcgill-femr/scipion-em-cryomethods
Author: Josue Gomez Blanco & Javier Vargas Balbuena
Author-email: josue.gomez-blanco@mcgill.ca
License: UNKNOWN
Project-URL: Source, https://github.com/mcgill-femr/scipion-em-cryomethods/
Project-URL: Bug Reports, https://github.com/mcgill-femr/scipion-em-cryomethods/issues/
Keywords: scipion electron-microscopy cryomethods structural-biology image-processing
Platform: UNKNOWN
Classifier: Development Status :: 5 - Production/Stable
Classifier: License :: OSI Approved :: GNU General Public License v3 (GPLv3)
Classifier: Programming Language :: Python :: 2.7
